pygourmet/__init__.py
pygourmet/api.py
pygourmet/error.py
hotpepper_gourmet-0.1.0.dist-info/LICENSE
hotpepper_gourmet-0.1.0.dist-info/WHEEL
hotpepper_gourmet-0.1.0.dist-info/METADATA
hotpepper_gourmet-0.1.0.dist-info/RECORD
