Metadata-Version: 2.1
Name: hotpepper-gourmet
Version: 0.1.0
Summary: A simple Python wrapper for Hotpepper API
Home-page: https://github.com/paperlefthand/hotpepper-gourmet
License: MIT
Author: paperlefthand
Author-email: being.paperlefthand@gmail.com
Requires-Python: >=3.10,<4.0
Classifier: Intended Audience :: Developers
Classifier: License :: OSI Approved :: MIT License
Classifier: Programming Language :: Python :: 3
Classifier: Programming Language :: Python :: 3.10
Classifier: Programming Language :: Python :: 3.11
Classifier: Programming Language :: Python :: 3.10
Classifier: Programming Language :: Python :: 3.11
Classifier: Programming Language :: Python :: Implementation :: CPython
Classifier: Topic :: Software Development :: Libraries :: Python Modules
Requires-Dist: requests (>=2.28,<3.0)
Project-URL: Repository, https://github.com/paperlefthand/hotpepper-gourmet
